LICENSE
README.md
pyproject.toml
search_bikeshed.egg-info/PKG-INFO
search_bikeshed.egg-info/SOURCES.txt
search_bikeshed.egg-info/dependency_links.txt
search_bikeshed.egg-info/entry_points.txt
search_bikeshed.egg-info/top_level.txt
searchbs/__init__.py