Metadata-Version: 2.4
Name: search-bikeshed
Version: 0.1.0
Summary: Index and search Bikeshed (.bs) source documents from URLs with efficient change detection
Author-email: Tarek Ziade <tarek@ziade.org>
License: MIT
Project-URL: Homepage, https://github.com/tarekziade/search-bs
Project-URL: Repository, https://github.com/tarekziade/search-bs
Keywords: bikeshed,search,indexing,full-text-search,documentation
Classifier: Development Status :: 4 - Beta
Classifier: Intended Audience :: Developers
Classifier: License :: OSI Approved :: MIT License
Classifier: Programming Language :: Python :: 3
Classifier: Programming Language :: Python :: 3.8
Classifier: Programming Language :: Python :: 3.9
Classifier: Programming Language :: Python :: 3.10
Classifier: Programming Language :: Python :: 3.11
Classifier: Programming Language :: Python :: 3.12
Classifier: Programming Language :: Python :: 3.13
Classifier: Topic :: Software Development :: Documentation
Classifier: Topic :: Text Processing :: Indexing
Requires-Python: >=3.8
License-File: LICENSE
Dynamic: license-file
